odoo/addons/sale_order_update_timesheet_price/README.rst
odoo/addons/sale_order_update_timesheet_price/__init__.py
odoo/addons/sale_order_update_timesheet_price/__manifest__.py
odoo/addons/sale_order_update_timesheet_price/i18n/it.po
odoo/addons/sale_order_update_timesheet_price/i18n/sale_order_update_timesheet_price.pot
odoo/addons/sale_order_update_timesheet_price/models/__init__.py
odoo/addons/sale_order_update_timesheet_price/models/account_analytic_line.py
odoo/addons/sale_order_update_timesheet_price/models/sale_order_line.py
odoo/addons/sale_order_update_timesheet_price/readme/CONTRIBUTORS.md
odoo/addons/sale_order_update_timesheet_price/readme/DESCRIPTION.md
odoo/addons/sale_order_update_timesheet_price/readme/USAGE.md
odoo/addons/sale_order_update_timesheet_price/security/ir.model.access.csv
odoo/addons/sale_order_update_timesheet_price/static/description/icon.png
odoo/addons/sale_order_update_timesheet_price/static/description/index.html
odoo/addons/sale_order_update_timesheet_price/tests/__init__.py
odoo/addons/sale_order_update_timesheet_price/tests/test_sale_order_timesheet_update_price.py
odoo/addons/sale_order_update_timesheet_price/views/sale_order_views.xml
odoo/addons/sale_order_update_timesheet_price/wizards/__init__.py
odoo/addons/sale_order_update_timesheet_price/wizards/sale_order_unit_price_update.py
odoo/addons/sale_order_update_timesheet_price/wizards/sale_order_unit_price_update.xml
odoo_addon_sale_order_update_timesheet_price-19.0.1.0.0.4.dist-info/METADATA
odoo_addon_sale_order_update_timesheet_price-19.0.1.0.0.4.dist-info/WHEEL
odoo_addon_sale_order_update_timesheet_price-19.0.1.0.0.4.dist-info/top_level.txt
odoo_addon_sale_order_update_timesheet_price-19.0.1.0.0.4.dist-info/RECORD
