Metadata-Version: 2.1
Name: odoo-addon-sale_order_update_timesheet_price
Version: 19.0.1.0.0.4
Requires-Dist: odoo==19.0.*
Summary: Update the unit price of already invoiced sale order lines by creating a new line
Home-page: https://github.com/OCA/timesheet
License: AGPL-3
Author: ACSONE SA/NV, Odoo Community Association (OCA)
Author-email: support@odoo-community.org
Classifier: Programming Language :: Python
Classifier: Framework :: Odoo
Classifier: Framework :: Odoo :: 19.0
Classifier: License :: OSI Approved :: GNU Affero General Public License v3
